SirkPire/__init__.py
SirkPire/cryption/__init__.py
SirkPire/handler/__init__.py
SirkPire/maker/__init__.py
SirkPire/message/__init__.py
SirkPire/methods/__init__.py
SirkPire/servers/__init__.py
SirkPire/sessions/__init__.py
SirkPire/tools/__init__.py
SirkPire-2.0.1.dist-info/METADATA
SirkPire-2.0.1.dist-info/WHEEL
SirkPire-2.0.1.dist-info/top_level.txt
SirkPire-2.0.1.dist-info/RECORD
