Metadata-Version: 2.1
Name: SirkPire
Version: 2.0.1
Summary: This is a powerful and easy library for building self Bots in Rubika
Home-page: https://github.com/MrTelepathic/SirkPire
Author: MrTelepathic
Author-email: shahrokhenhedam@gmail.com
Keywords: rubika,rubika-bot,SirkPire,rubx,rubino,rubika.ir,bot,Rubipy
Classifier: Programming Language :: Python :: 3.6
Classifier: Programming Language :: Python :: 3.7
Classifier: Programming Language :: Python :: 3.8
Classifier: Programming Language :: Python :: 3.9
Classifier: Programming Language :: Python :: 3.10
Classifier: Programming Language :: Python :: 3.11
Classifier: Programming Language :: Python :: 3.12
Classifier: License :: OSI Approved :: MIT License
Requires-Python: ~=3.6
Requires-Dist: pycryptodome
Requires-Dist: websocket-client
Requires-Dist: requests
Requires-Dist: urllib3
Requires-Dist: pillow
Requires-Dist: mutagen
Requires-Dist: tinytag
